<?xml version="1.0" encoding="utf-8"?>
<!DOCTYPE hibernate-mapping PUBLIC "-//Hibernate/Hibernate Mapping DTD 3.0//EN"
"http://hibernate.sourceforge.net/hibernate-mapping-3.0.dtd">
<!-- 
    Mapping file autogenerated by MyEclipse Persistence Tools
-->
<hibernate-mapping>
    <class name="com.sunflower.back.domain.admin.AdminUser" table="admin_user" dynamic-insert="true" dynamic-update="true">
        <id name="id" type="integer">
            <column name="id" />
            <generator class="identity" />
        </id>
        <property name="nickname" type="string">
            <column name="nickname" length="50" not-null="true">
                <comment>昵称</comment>
            </column>
        </property>
        <property name="username" type="string">
            <column name="username" length="50" not-null="true">
                <comment>用户名</comment>
            </column>
        </property>
        <property name="psw" type="string">
            <column name="psw" length="50" not-null="true">
                <comment>登录密码</comment>
            </column>
        </property>
        <property name="dateAdded" type="java.util.Date">
            <column name="date_added" length="19">
                <comment>创建时间</comment>
            </column>
        </property>
        <property name="lastLoginDate" type="java.util.Date">
            <column name="last_login_date" length="19">
                <comment>最近登录时间</comment>
            </column>
        </property>
        <property name="loginCount" type="integer">
            <column name="login_count">
                <comment>登录次数</comment>
            </column>
        </property>
        <property name="lastLoginIp" type="string">
            <column name="last_login_ip" length="20">
                <comment>登录IP</comment>
            </column>
        </property>
        <property name="status" type="integer">
            <column name="status" not-null="true">
                <comment>账号状态</comment>
            </column>
        </property>
        <property name="groupId" type="integer">
            <column name="group_id">
                <comment>组织部门id</comment>
            </column>
        </property>
    </class>
</hibernate-mapping>
